oss/__init__.py
oss/api.py
oss/auth.py
oss/compat.py
oss/crc64_combine.py
oss/defaults.py
oss/entity.py
oss/exceptions.py
oss/headers.py
oss/http.py
oss/select_params.py
oss/select_response.py
oss/utils.py
oss/xml_utils.py
osstool-1.0.0.dist-info/METADATA
osstool-1.0.0.dist-info/WHEEL
osstool-1.0.0.dist-info/license.txt
osstool-1.0.0.dist-info/top_level.txt
osstool-1.0.0.dist-info/RECORD
