Metadata-Version: 2.1
Name: osstool
Version: 1.0.0
Summary: OSS Python SDK
Home-page: https://github.com/ybwang0211/oss-python-sdk
Author: wangyingbin
Author-email: 869063218@qq.com
License-File: license.txt
Requires-Dist: requests (!=2.9.0)
Requires-Dist: crcmod (>=1.7)
